quantsapp/__init__.py
quantsapp/_config.py
quantsapp/_enum_meta.py
quantsapp/_enums.py
quantsapp/_logger.py
quantsapp/_market_timings.py
quantsapp/_master_data.py
quantsapp/_models.py
quantsapp/_utils.py
quantsapp/_version.py
quantsapp/constants.py
quantsapp/exceptions.py
quantsapp/response.py
quantsapp/variables.py
quantsapp/_api_helper/__init__.py
quantsapp/_api_helper/_config.py
quantsapp/_api_helper/_main.py
quantsapp/_api_helper/_models.py
quantsapp/_execution/__init__.py
quantsapp/_execution/_cache.py
quantsapp/_execution/_config.py
quantsapp/_execution/_enums.py
quantsapp/_execution/_main.py
quantsapp/_execution/_models.py
quantsapp/_execution/_utils.py
quantsapp/_execution/_variables.py
quantsapp/_execution/_modules/__init__.py
quantsapp/_execution/_modules/_book_update.py
quantsapp/_execution/_modules/_book_update_models.py
quantsapp/_execution/_modules/_broker_add.py
quantsapp/_execution/_modules/_broker_add_models.py
quantsapp/_execution/_modules/_broker_delete.py
quantsapp/_execution/_modules/_broker_delete_models.py
quantsapp/_execution/_modules/_broker_list.py
quantsapp/_execution/_modules/_broker_list_models.py
quantsapp/_execution/_modules/_broker_login_data.py
quantsapp/_execution/_modules/_broker_login_data_models.py
quantsapp/_execution/_modules/_broker_ws_conn.py
quantsapp/_execution/_modules/_broker_ws_conn_models.py
quantsapp/_execution/_modules/_order_cancel.py
quantsapp/_execution/_modules/_order_cancel_models.py
quantsapp/_execution/_modules/_order_list.py
quantsapp/_execution/_modules/_order_list_models.py
quantsapp/_execution/_modules/_order_logs.py
quantsapp/_execution/_modules/_order_logs_models.py
quantsapp/_execution/_modules/_order_modify.py
quantsapp/_execution/_modules/_order_modify_models.py
quantsapp/_execution/_modules/_order_place.py
quantsapp/_execution/_modules/_order_place_models.py
quantsapp/_execution/_modules/_position_list.py
quantsapp/_execution/_modules/_position_list_models.py
quantsapp/_login/__init__.py
quantsapp-0.0.1rc1.dist-info/METADATA
quantsapp-0.0.1rc1.dist-info/WHEEL
quantsapp-0.0.1rc1.dist-info/licenses/LICENSE
quantsapp-0.0.1rc1.dist-info/RECORD
