Metadata-Version: 2.4
Name: quantsapp
Version: 0.0.1rc1
Summary: Quantsapp
Project-URL: Homepage, https://github.com/quantsapp/python-sdk
Project-URL: Issues, https://github.com/quantsapp/python-sdk/issues
Author-email: Quantsapp <support@quantsapp.com>
License-Expression: MIT
License-File: LICENSE
Classifier: Operating System :: OS Independent
Classifier: Programming Language :: Python :: 3
Classifier: Programming Language :: Python :: 3.12
Classifier: Programming Language :: Python :: 3.13
Requires-Python: >=3.12
Requires-Dist: pydantic~=2.11.4
Requires-Dist: websocket-client~=1.8.0
